{"name": "All Betts Are Off", "ingredients": [{"quantity": "1 1/2", "item": "Sombra mezcal", "unit": "oz"}, {"quantity": "3/4", "item": "Dolin blanc vermouth", "unit": "oz"}, {"quantity": "3/4", "item": "Yellow Chartreuse", "unit": "oz"}, {"quantity": "2", "item": "dashes", "unit": "dashes"}], "garnish": ["1\u00a0Grapefruit twist"], "glass": "Cocktail", "preparation": "Add all the ingredients to a mixing glass and fill with ice.\nStir, and strain into a chilled cocktail glass.\nSqueeze a grapefruit twist over the drink and use as a garnish.", "imageURL": "//cdn.liquor.com/wp-content/uploads/2011/03/all-betts-are-off1.jpg"}