{"name": "Baileys Mocha Monkey", "ingredients": [{"quantity": null, "item": "Chocolate syrup", "unit": null}, {"quantity": "1 1/2", "item": "Baileys with a Hint of Coffee", "unit": "oz"}, {"quantity": "1", "item": "Vanilla ice cream (softened)", "unit": "scoop"}, {"quantity": "1", "item": "Banana, peeled and sliced", "unit": null}], "garnish": ["1\u00a0Banana slice and coffee beans"], "glass": "Highball", "preparation": "Swirl the inside of a highball glass with chocolate syrup.\nAdd the remaining ingredients to a blender and fill with ice.\nBlend until smooth and pour into the prepared glass.\nGarnish with a banana slice and 3 coffee beans.", "imageURL": "//cdn.liquor.com/wp-content/uploads/2010/01/baileys-mocha-monkey.jpg"}