{"name": "Boilermaker", "ingredients": [{"quantity": "1", "name": "Bourbon or rye whiskey", "unit": "oz", "isGarnish": false}, {"quantity": "", "name": "Beer", "unit": "", "isGarnish": false}], "preparation": "Go old-school with this straightforward whiskey and beer concoction.\n\nPour the whiskey into a shot glass.\n\nFill a pint glass halfway with beer.\n\nDrop the shot glass into the beer.", "imageURL": "https://www.liquor.com/thmb/su_xkDEQgfXJ-KClHPx0TDpcDGM=/960x0/filters:no_upscale():max_bytes(150000):strip_icc()/__opt__aboutcom__coeus__resources__content_migration__liquor__2014__02__15123838__boilermaker-720-720-recipe-fd9d6a89c5d64f25adb65652ad1a7f1e.jpg", "authorName": "Liquor.com", "reviewCount": 16, "avgRating": 4.0}