{"name": "Busy Bee", "ingredients": [{"quantity": "2", "name": "Ransom Old Tom gin", "unit": "oz", "isGarnish": false}, {"quantity": "1/2", "name": "Salted cucumber juice*", "unit": "oz", "isGarnish": false}, {"quantity": "1/2", "name": "Honey", "unit": "oz", "isGarnish": false}, {"quantity": "1/4", "name": "Fresh lemon juice", "unit": "oz", "isGarnish": false}, {"quantity": "", "name": "Rosemary sprig", "unit": "", "isGarnish": true}], "preparation": "When Allison Lindsey, the head bartender at Baltimore\u2019s Bar Vasquez, is juicing cucumbers for this salty riff on the Bee\u2019s Knees, she starts with no more than a teaspoon or so of sea salt per quart. \u201cYou have your sweet, your bitter, your salty and the aromatics,\u201d she says. \u201cIt makes a great well-balanced cocktail and something a little unexpected.\u201d\n\nAdd all ingredients into a shaker with ice and shake until well-chilled.\n\nStrain into a chilled coupe glass, and garnish with a rosemary sprig.\n\n*Salted cucumber juice: Using a juicer, juice peeled cucumbers to yield 1 quart. Strain juice to remove any pulp, and add 1 to 1 1/2 tsp sea salt to add flavor and preserve the juice. Store the mixture in the refrigerator.", "imageURL": "https://www.liquor.com/thmb/Q3mkggSomIjLjTocBlo6hA8rRGc=/960x0/filters:no_upscale():max_bytes(150000):strip_icc()/__opt__aboutcom__coeus__resources__content_migration__liquor__2017__06__20135933__Busy-Bee-720x720-recipe-c173699136ed484f8abcc08d1f0e15a0.jpg", "authorName": "Allison Lindsey", "reviewCount": null, "avgRating": null}