{"name": "Cadbury Creme Egg", "ingredients": [{"quantity": "2", "item": "Vanilla vodka", "unit": "oz"}, {"quantity": "1/2", "item": "Yellow Chartreuse", "unit": "oz"}, {"quantity": "1/2", "item": "White cr\u00e8me de cacao", "unit": "oz"}, {"quantity": "1", "item": "Heavy cream", "unit": "oz"}], "garnish": ["Shaved chocolate", "1\u00a0oz\u00a0semisweet or dark chocolate", "Cadbury Creme Mini Egg"], "glass": "Coupe", "preparation": "Grate or chop the chocolate and place in a small shallow bowl or rimmed plate. Melt on low heat in the microwave. Dip the rim of the cocktail glass in the chocolate, and chill to set.\nCombine the vodka, Chartreuse, cr\u00e8me de cacao and cream in a cocktail shaker with ice and shake well.\nStrain into the chocolate-rimmed glass.\nGrate additional chocolate curls over the top of the drink.\nTop with a Cadbury Creme Mini Egg, cut open to reveal the \"yolk.\"", "imageURL": "//cdn.liquor.com/wp-content/uploads/2017/03/08150527/cadburry-egg-ccotkail-720x720-article.jpg"}