{"name": "Tequila Manhattan", "ingredients": [{"quantity": "1 1/2", "item": "Cazadores reposado tequila", "unit": "oz", "isGarnish": false}, {"quantity": "1", "item": "Sweet vermouth", "unit": "oz", "isGarnish": false}, {"quantity": "1/2", "item": "Fernet", "unit": "oz", "isGarnish": false}, {"quantity": "2", "item": "Chocolate-mole bitters", "unit": "dashes", "isGarnish": false}, {"quantity": "", "item": "Orange peel", "unit": "", "isGarnish": true}], "preparation": "Is it still a Manhattan when it\u2019s made with tequila? Who cares when a drink is this satisfying?\n\nCombine all the ingredients in mixing glass with ice, and stir 25 to 30 times.\n\nStrain into a rocks glass over ice, and garnish with an orange peel.", "imageURL": "https://www.liquor.com/thmb/wLdhOLP1eLpeK27u0-WOC5M3CWc=/960x0/filters:no_upscale():max_bytes(150000):strip_icc()/__opt__aboutcom__coeus__resources__content_migration__liquor__2017__08__25152007__MANHATTAN-720x720-ec42c690eeb44bf5b85f7bde8d12391e.jpg", "authorName": "Matt Armato", "reviewCount": null, "avgRating": null}