{"name": "Don't Call Me Shirley", "ingredients": [{"quantity": "1 1/2", "name": "House-made true grenadine*", "unit": "oz", "isGarnish": false}, {"quantity": "1/2", "name": "Fresh lemon juice", "unit": "oz", "isGarnish": false}, {"quantity": "1/2", "name": "Fresh lime juice", "unit": "oz", "isGarnish": false}, {"quantity": "6", "name": "Club soda", "unit": "oz", "isGarnish": false}, {"quantity": "", "name": "Amarena cherries", "unit": "", "isGarnish": true}], "preparation": "Colleen Kenny, the bar manager of Nostrana in Portland, Ore., serves customers this version of the Shirley Temple. \u201cIt\u2019s a fun way to let them drink something that\u2019s special when they\u2019re eating out,\u201d she says. \u201cI drank them all the time when eating out with my parents. It\u2019s always consistent. We call ours Don\u2019t Call Me Shirley because you\u2019re not getting the scary, cloying syrup that people are used to.\u201d\n\nThis recipe originally appeared as part of \u201cIt\u2019s Time to Stop Hating the Shirley Temple.\u201d\n\nAdd all ingredients into a Collins glass.\n\nStir and add ice.\n\nGarnish with 2 skewered amarena cherries.\n\n*House-made true grenadine: Bring 16 oz pomegranate juice to a simmer. Add 2 oz pomegranate molasses. Cool to room temperature. Whisk in 16 oz sugar. Add 1 tsp orange flower water. Strain through a fine filter.", "imageURL": "https://www.liquor.com/thmb/_UAnoDUzKGPTVkZBOMKG6Npqrrk=/960x0/filters:no_upscale():max_bytes(150000):strip_icc()/__opt__aboutcom__coeus__resources__content_migration__liquor__2019__12__31121108__Dont-Call-Me-Shirley-720x720-recipe-b1cafe7cb5814c6299fa47c5e7f98bdf.jpg", "authorName": "Liquor.com", "reviewCount": null, "avgRating": null}