{"name": "Downhill Daring", "ingredients": [{"quantity": "1 1/2", "item": "Punt e Mes", "unit": "oz", "isGarnish": false}, {"quantity": "1/2", "item": "Cocchi Americano aperitivo", "unit": "oz", "isGarnish": false}, {"quantity": "1/4", "item": "B\u00e9n\u00e9dictine", "unit": "oz", "isGarnish": false}, {"quantity": "1", "item": "Old Forester Signature bourbon", "unit": "oz", "isGarnish": false}, {"quantity": "2", "item": "Angostura bitters", "unit": "dashes", "isGarnish": false}, {"quantity": "2", "item": "Regan\u2019s Orange Bitters No. 6", "unit": "dashes", "isGarnish": false}, {"quantity": "", "item": "Orange peel", "unit": "", "isGarnish": true}], "preparation": "The Brooklyn cocktail and Philip Greene\u2019s recent book \u201cA Drinkable Feast\u201d about 1920s Parisian libations influenced this drink, whose name is inspired by a Norman Rockwell piece. The roasty chocolate notes of Punt e Mes pair with B\u00e9n\u00e9dictine\u2019s herbaceousness and the sweet flavor of Cocchi Americano aperitivo. \u201cIt's a spirituous cocktail without being as dangerous as a standard Manhattan,\u201d says Brian Nixon, the general manager of Truxton Inn and McClellan\u2019s Retreat in Washington, D.C.\n\nThis recipe originally appeared as part of \u201c5 Modern Riffs on the Reverse Manhattan.\u201d\n\nAdd all ingredients into a mixing glass with ice and stir until well-chilled.\n\nStrain into a chilled coupe.\n\nExpress the oil from an orange peel over the glass and rest it on the rim.", "imageURL": "https://www.liquor.com/thmb/dJrRBN39bRbEdaivby3jx5gOClc=/960x0/filters:no_upscale():max_bytes(150000):strip_icc()/__opt__aboutcom__coeus__resources__content_migration__liquor__2019__01__14084856__downhill-daring-720x720-recipe-f505cfe132274629afc35ce509ac4d7c.jpg", "authorName": "Brian Nixon", "reviewCount": null, "avgRating": null}