{"name": "Duck Hunt", "ingredients": [{"quantity": "8 1/2", "name": "Duck stock, strained", "unit": "oz", "isGarnish": false}, {"quantity": "", "name": "Half egg white", "unit": "", "isGarnish": false}, {"quantity": "1", "name": "Cold water", "unit": "tbsp", "isGarnish": false}, {"quantity": "1/2", "name": "g Maldon sea salt", "unit": "", "isGarnish": false}, {"quantity": "1/2", "name": "g Smoked black pepper", "unit": "", "isGarnish": false}, {"quantity": "3 1/2", "name": "Dolin G\u00e9n\u00e9py des Alpes liqueur", "unit": "oz", "isGarnish": false}, {"quantity": "1/5", "name": "St. George Absinthe Verte", "unit": "oz", "isGarnish": false}, {"quantity": "", "name": "Toasted juniper berries", "unit": "", "isGarnish": true}, {"quantity": "", "name": "Whole caraway seeds", "unit": "", "isGarnish": true}, {"quantity": "", "name": "Rosemary sprig", "unit": "", "isGarnish": true}], "preparation": "Ambitious home cooks who want to add some fancy French flavors to their cocktail glasses should try this duck-stock-based drink by Eric Rivera, the executive chef at Seattle\u2019s The Bookstore Bar & Caf\u00e9, that will seriously impress dinner guests.\n\nIn a small saucepan, warm the duck stock. In a small bowl, combine the egg white and cold water, then stir that mixture into the warm stock. Bring to a simmer. Remove pan from heat and let stand for 5 minutes. (As the egg white cooks, it will coagulate and trap fine particles from the stock.) Pour the stock through cheesecloth into a small, clean bowl to strain out the particles and egg white. Add the salt and smoked pepper.\n\nPour the seasoned stock, G\u00e9n\u00e9py and absinthe into a rocks glass.\n\nGarnish with toasted juniper berries, whole caraway seeds and a rosemary sprig.", "imageURL": "https://www.liquor.com/thmb/QiQfw74RTx7-Fi-B7J83rAWb3k8=/960x0/filters:no_upscale():max_bytes(150000):strip_icc()/__opt__aboutcom__coeus__resources__content_migration__liquor__2017__01__20133627__duck-hunt-720x720-recipe-badf1fbd913d4db595a1bc09cf13f0d7.jpg", "authorName": "Eric Rivera", "reviewCount": null, "avgRating": null}