{"name": "Earl Grey MarTEAni", "ingredients": [{"quantity": "1 1/2", "item": "Earl Grey\u2013tea-infused Tanqueray gin *", "unit": "oz", "isGarnish": false}, {"quantity": "3/4", "item": "Fresh lemon juice", "unit": "oz", "isGarnish": false}, {"quantity": "1", "item": "Simple syrup", "unit": "oz", "isGarnish": false}, {"quantity": "1", "item": "Egg white", "unit": "", "isGarnish": false}, {"quantity": "", "item": "Sugar rim", "unit": "", "isGarnish": true}, {"quantity": "", "item": "Lemon twist", "unit": "", "isGarnish": true}], "preparation": "This original twist on the Gin Sour comes by way of one of the pioneers of the modern cocktail movement, Audrey Saunders of New York City\u2019s Pegu Club.\n\nTake a chilled coupe glass, half-rim it with sugar and set aside.\n\nPour all ingredients into a shaker without ice and dry-shake vigorously (at least 10 seconds).\n\nAdd ice and shake again.\n\nStrain into prepared coupe.\n\nGarnish with a lemon twist.\n\n*Earl Grey tea-infused Tanqueray gin: Add 4 tbsp Earl Grey tea leaves into a 750 mL bottle of Tanqueray gin (or other high-proof dry gin), cap and shake. Let sit at room temperature for at least 2 hours. Strain the infused gin through a coffee filter into a separate container. Rinse out bottle to remove loose tea, and pour gin back into clean bottle. Can be stored indefinitely if refrigerated.", "imageURL": "https://www.liquor.com/thmb/1QL-_0RAxZ9tTivrhVssd8pYTYI=/960x0/filters:no_upscale():max_bytes(150000):strip_icc()/__opt__aboutcom__coeus__resources__content_migration__liquor__2019__03__29143959__Early-Grey-Marteani-720x720-recipe-f589346d29b346dbad2ae47afe1494b5.jpg", "authorName": "Liquor.com", "reviewCount": 5, "avgRating": 5.0}