{"name": "Espresso Old Fashioned", "ingredients": [{"quantity": "2", "item": "Redemption rye whiskey", "unit": "oz"}, {"quantity": "2", "item": "Espresso or cold-brew coffee", "unit": "oz"}, {"quantity": "1/4", "item": "Simple syrup", "unit": "oz"}, {"quantity": "1", "item": "dash", "unit": "dashes"}, {"quantity": "1", "item": "dash", "unit": "dashes"}], "garnish": ["Lemon twist"], "glass": "Old Fashioned/Rocks", "preparation": "Rinse an Old Fashioned glass with the absinthe and set aside.\nAdd remaining ingredients into a mixing glass with ice and stir.\nStrain into the prepared glass over ice.\nExpress the oil from a lemon twist and drop in as a garnish.", "imageURL": "//cdn.liquor.com/wp-content/uploads/2019/03/12134252/espresso-old-fashioned_1080x1080-1024x1024.jpg"}