{"name": "Flannel", "ingredients": [{"quantity": "1", "item": "Cognac", "unit": "oz"}, {"quantity": "1/2", "item": "Apple cider syrup*", "unit": "oz"}, {"quantity": "1/4", "item": "Allspice dram", "unit": "oz"}, {"quantity": "1/4", "item": "Orange juice", "unit": "oz"}], "garnish": ["1\u00a0Orange peel"], "glass": "Old Fashioned", "preparation": "Add all ingredients to a shaker and fill with ice.\nShake vigorously, and strain into an Old Fashioned glass over a large ice cube.\nGarnish with an orange peel.", "imageURL": "//cdn.liquor.com/wp-content/uploads/2014/10/the-flannel-cocktail-recipe.jpg"}