{"name": "Flor Old Fashioned", "ingredients": [{"quantity": "2", "name": "Flor de Ca\u00f1a 12-year-old rum", "unit": "oz", "isGarnish": false}, {"quantity": "1/2", "name": "Simple syrup", "unit": "oz", "isGarnish": false}, {"quantity": "2", "name": "Angostura bitters", "unit": "dashes", "isGarnish": false}, {"quantity": "2", "name": "Orange bitters", "unit": "dashes", "isGarnish": false}, {"quantity": "", "name": "Cherry", "unit": "", "isGarnish": true}], "preparation": "Who said you can\u2019t teach an Old Fashioned new tricks? The Flor Old Fashioned uses ultra-premium aged rum to give the classic cocktail a whole new flavor profile.\n\nAdd all ingredients into a mixing glass with ice and stir.\n\nStrain into an Old Fashioned glass over fresh ice.\n\nGarnish with a cherry.", "imageURL": "https://www.liquor.com/thmb/0_ytIhFkNFetL_tUNuhyKwfJdF8=/960x0/filters:no_upscale():max_bytes(150000):strip_icc()/__opt__aboutcom__coeus__resources__content_migration__liquor__2019__04__25113252__Flor-oldfashioned-feature-5e888b29641c4a5ea1fb7b06c2647178.jpg", "authorName": "Liquor.com", "reviewCount": null, "avgRating": null}