{"name": "Gibson", "ingredients": [{"quantity": "2 1/2", "name": "Gin or vodka", "unit": "oz", "isGarnish": false}, {"quantity": "1/2", "name": "Dry vermouth", "unit": "oz", "isGarnish": false}, {"quantity": "", "name": "Cocktail onion", "unit": "", "isGarnish": true}], "preparation": "The Martini's savory second cousin, the Gibson, uses a pickled cocktail onion in place of the typical briny olive to add an umami undertone to the classic cocktail. The Gibson is believed to have been created by San Francisco businessman Walter D.K. Gibson in the late 1800s, who thought that eating onions prevented colds, hence the addition of the mini allium.\n\nAdd the ingredients into a mixing glass with ice and stir.\n\nStrain into a chilled cocktail glass.\n\nGarnish with a cocktail onion.", "imageURL": "https://www.liquor.com/thmb/QL-MJPfvB4EUf92TAd28Hr8gUuk=/960x0/filters:no_upscale():max_bytes(150000):strip_icc()/__opt__aboutcom__coeus__resources__content_migration__liquor__2019__08__23101503__gibson-720x720-recipe-29c40dea629049b09d096da221cdd618.jpg", "authorName": "Liquor.com", "reviewCount": 13, "avgRating": 4.5}