{"name": "Gimlet", "ingredients": [{"quantity": "2 1/2", "item": "gin", "unit": "oz", "isGarnish": false}, {"quantity": "1/2", "item": "fresh lime juice", "unit": "oz", "isGarnish": false}, {"quantity": "1/2", "item": "simple syrup", "unit": "oz", "isGarnish": false}, {"quantity": "", "item": "lime wheel", "unit": "", "isGarnish": true}], "preparation": "Who says medicine can't taste amazing? This essential cocktail was created for sailors as a way to prevent scurvy. It didn't take long to realize that this preventative drink was also delicious. While scurvy may be of the past, it seems like this tart tipple is here to stay. It doesn't get much simpler or more refreshing than the classic Gimlet.\n\nAdd all ingredients into a shaker with ice and shake.\n\nStrain into a chilled cocktail glass or an Old Fashioned glass filled with fresh ice.\n\nGarnish with a lime wheel.\n\n(You can substitute 1 oz lime cordial, such as Rose's lime juice, for both the lime juice and simple syrup.).", "imageURL": "https://www.liquor.com/thmb/wamrW8uPQzd29ZHnUcHUIMkAuFA=/960x0/filters:no_upscale():max_bytes(150000):strip_icc()/__opt__aboutcom__coeus__resources__content_migration__liquor__2019__01__10072454__gimlet-720x720-recipe-a0d317f2ce7b4818a0fdbd2bbaaaf2c9.jpg", "authorName": "Liquor.com", "reviewCount": 60, "avgRating": 4.5}