{"name": "Harvest Time", "ingredients": [{"quantity": "3/4", "item": "BenRiach Curiositas peated 10-year-old scotch", "unit": "oz"}, {"quantity": "1/4", "item": "Campari liqueur", "unit": "oz"}, {"quantity": "1/2", "item": "Ginger syrup**", "unit": "oz"}, {"quantity": "1/2", "item": "Yuzu or lemon juice", "unit": "oz"}, {"quantity": "4", "item": "Warm apple cider", "unit": "oz"}], "garnish": ["Cloves", "Cinnamon powder", "Lemon wheel"], "glass": "Heatproof mug or glass", "preparation": "Bring the apple cider to a simmer in a medium saucepan.\nAdd the scotch, liqueur, syrup and juice, and stir until warm.\nRemove from heat, and pour into a heatproof mug or glass.\nGarnish with a sprinkle of cinnamon powder and a lemon wheel studded with 3 cloves.\n*Ginger syrup: Pur\u00e9e 2 cups peeled sliced ginger and 2 cups boiling water on high in a Vitamix. Add 4 cups light brown sugar and stir to combine. Let macerate for a day, strain out solids and store syrup in the refrigerator.", "imageURL": "//cdn.liquor.com/wp-content/uploads/2018/01/25135348/harvest-time-720x720-recipe.jpg"}