{"name": "Belle Amie", "ingredients": [{"quantity": "1", "name": "Hennessy V.S.O.P Privil\u00e8ge cognac", "unit": "oz", "isGarnish": false}, {"quantity": "3/4", "name": "Fig vodka", "unit": "oz", "isGarnish": false}, {"quantity": "3/4", "name": "Fresh lime juice", "unit": "oz", "isGarnish": false}, {"quantity": "1/2", "name": "Simple syrup", "unit": "oz", "isGarnish": false}, {"quantity": "1", "name": "Fee Brothers Aztec chocolate bitters", "unit": "dashes", "isGarnish": false}, {"quantity": "", "name": "Dehydrated orange wheel", "unit": "", "isGarnish": true}], "preparation": "Bea\u2019s twist on an Old Fashioned hits sweet, tart, and chocolate-y notes.\n\nAdd all the ingredients to a shaker with ice and shake.\n\nStrain over fresh ice in a rocks glass.\n\nGarnish with a dehydrated orange wheel.", "imageURL": "https://www.liquor.com/thmb/5CYGaxywTxLeTboUz7qZVn3E8qs=/960x0/filters:no_upscale():max_bytes(150000):strip_icc()/__opt__aboutcom__coeus__resources__content_migration__liquor__2017__06__23131033__BEA-13-of-251-28b7301250fd42138f2042eef392debf.jpg", "authorName": "Liquor.com", "reviewCount": null, "avgRating": null}