{"name": "High King Highball", "ingredients": [{"quantity": "2", "item": "Clontarf Irish whiskey", "unit": "oz", "isGarnish": false}, {"quantity": "1/2", "item": "Aperol", "unit": "oz", "isGarnish": false}, {"quantity": "1/2", "item": "Simple syrup", "unit": "oz", "isGarnish": false}, {"quantity": "1", "item": "Peychaud's bitters", "unit": "dashes", "isGarnish": false}, {"quantity": "3/4", "item": "Fresh lemon juice", "unit": "oz", "isGarnish": false}, {"quantity": "3/4", "item": "Fresh grapefruit juice", "unit": "oz", "isGarnish": false}, {"quantity": "3", "item": "Raspberries, muddled", "unit": "", "isGarnish": false}, {"quantity": "", "item": "Skewered lemon wheel and raspberry", "unit": "", "isGarnish": true}], "preparation": "At East Village cocktail destination Pouring Ribbons, cocktails get \u201crated\u201d on a scale of \u201crefreshing\u201d to \u201cspirituous,\u201d \u201ccomforting\u201d to \u201cadventurous,\u201d to help guide you to the right drink. (Chartreuse lovers, ask for the bar\u2019s vintage Chartreuse selection). On the refreshing side, the High King Highball was created by bar-star Joaqu\u00edn Sim\u00f3n and features Clontarf Irish whiskey and Aperol, along with muddled raspberries, lemon and grapefruit juices, simple syrup, Peychaud's bitters and a splash of soda. The artful creation is then garnished with a skewered lemon wheel and raspberry.\n\nPour the soda water into Collins glass with ice cubes.\n\nAdd all the other ingredients to a shaker with ice and shake.\n\nFine-strain into the Collins glass.\n\nGarnish with a skewered lemon wheel and raspberry.", "imageURL": "https://www.liquor.com/thmb/q0SNlrn3egf_YwTO5P7VODRouEw=/960x0/filters:no_upscale():max_bytes(150000):strip_icc()/__opt__aboutcom__coeus__resources__content_migration__liquor__2017__05__30111739__pouring-ribbons-king-highball-720x720-recipe-b8f0f55171144e75b8833ee1c480a551.jpg", "authorName": "Liquor.com", "reviewCount": null, "avgRating": null}