{"name": "Holiday Sparkler Wine", "ingredients": [{"quantity": "2", "name": "Yellowtail Sparkling Rose", "unit": "oz", "isGarnish": false}, {"quantity": "1/2", "name": "Elderflower liqueur", "unit": "oz", "isGarnish": false}, {"quantity": "1", "name": "Cranberry juice", "unit": "oz", "isGarnish": false}, {"quantity": "", "name": "Orange bitters", "unit": "", "isGarnish": false}, {"quantity": "", "name": "Sugar cube", "unit": "", "isGarnish": false}, {"quantity": "", "name": "rock candy stir stick", "unit": "", "isGarnish": true}], "preparation": "Sparks will fly with this sparkling rose and cranberry juice cocktail.\n\nSoak a sugar cube in orange bitters.\n\nPlace it in a flute.\n\nAdd elderflower liqueur and cranberry juice and gently top off the drink with Yellow Tail Rose.\n\nGarnish with a rock candy stir stick.", "imageURL": "https://www.liquor.com/thmb/tvEPW8JwUfZBORC94y2D65u8yr4=/960x0/filters:no_upscale():max_bytes(150000):strip_icc()/__opt__aboutcom__coeus__resources__content_migration__liquor__2017__12__27091652__11-Essential-Cocktails-for-Your-New-Years-Eve-Parties-720x720-article-96da72702d724028af8013f9fa830560.jpg", "authorName": "Yellowtail", "reviewCount": null, "avgRating": null}