{"name": "Hot Gin Punch", "ingredients": [{"quantity": "24", "item": "Hendrick's gin", "unit": "oz"}, {"quantity": "24", "item": "Madeira wine", "unit": "oz"}, {"quantity": "6", "item": "Lemon twists", "unit": null}, {"quantity": "1", "item": "Orange slice", "unit": null}, {"quantity": "3", "item": "chunks Pineapple", "unit": null}, {"quantity": "3", "item": "Honey", "unit": "oz"}, {"quantity": "1", "item": "Fresh lemon juice", "unit": "oz"}, {"quantity": "3", "item": "Cloves", "unit": null}, {"quantity": "1", "item": "Ground nutmeg", "unit": "pinch"}, {"quantity": "1", "item": "Ground cinnamon", "unit": "tsp"}, {"quantity": "1", "item": "Brown sugar", "unit": "tsp"}], "garnish": ["Cloves", "orange slices"], "glass": "Punch", "preparation": "Add all ingredients into a large saucepan and simmer over low heat for about 20 minutes.\nTo serve, pour the hot mixture into a punch bowl or teapot and garnish with orange slices studded with cloves.\nPair with gingerbread.", "imageURL": "//cdn.liquor.com/wp-content/uploads/2018/11/19130818/hendricks-hot-gin-punch-720x720-recipe.jpg"}