{"name": "Hot Buttered Rum Batter", "ingredients": [{"quantity": "1", "item": "lb Butter", "unit": "", "isGarnish": false}, {"quantity": "1", "item": "lb Brown sugar", "unit": "", "isGarnish": false}, {"quantity": "1", "item": "lb Sugar", "unit": "", "isGarnish": false}, {"quantity": "1", "item": "Ground cinnamon", "unit": "tbsp", "isGarnish": false}, {"quantity": "1", "item": "Ground clove", "unit": "tsp", "isGarnish": false}, {"quantity": "1", "item": "Ground nutmeg", "unit": "tsp", "isGarnish": false}, {"quantity": "1", "item": "qt Vanilla ice cream, softened slightly", "unit": "", "isGarnish": false}], "preparation": "Use this base to make the perfect Hot Buttered Rum in a snap.\n\nAdd all the ingredients except the ice cream to a bowl and stir to combine.\n\nAdd the ice cream and stir again.\n\nTransfer to a container with a lid, seal and store in the freezer.\n\nRefer to the Hot Buttered Rum recipe to build the drink.", "imageURL": "https://www.liquor.com/thmb/HZex4P8RLCLQd5Ekr5Rd_r2iM3M=/960x0/filters:no_upscale():max_bytes(150000):strip_icc()/__opt__aboutcom__coeus__resources__content_migration__liquor__2014__03__13193055__hot-buttered-rum-batter-720x720-recipe-f1c0dd766e414ae78e574b6961382cde.jpg", "authorName": "Liquor.com", "reviewCount": null, "avgRating": null}