{"name": "Hot Shot", "ingredients": [{"quantity": "1/2", "name": "Galliano L'Autentico", "unit": "oz", "isGarnish": false}, {"quantity": "1/2", "name": "espresso", "unit": "oz", "isGarnish": false}, {"quantity": "1/2", "name": "Heavy cream", "unit": "oz", "isGarnish": false}], "preparation": "It takes a steady hand to make this layered shot.\n\nCarefully layer the ingredients in a shot glass in the order shown (Galliano on the bottom, cream on the top).", "imageURL": "https://www.liquor.com/thmb/V5eTC1Ddz2ZnuqF-Bg48bYm7pYQ=/960x0/filters:no_upscale():max_bytes(150000):strip_icc()/__opt__aboutcom__coeus__resources__content_migration__liquor__2009__11__07212452__hot-shot-34d2486188bd4ec5beadbd94623f0364.jpg", "authorName": "Galliano", "reviewCount": null, "avgRating": null}