{"name": "Joan Collins", "ingredients": [{"quantity": "1/2", "name": "Lime, sliced", "unit": "", "isGarnish": false}, {"quantity": "2", "name": "slices Cucumber", "unit": "", "isGarnish": false}, {"quantity": "2", "name": "Mint leaves", "unit": "", "isGarnish": false}, {"quantity": "2", "name": "Vodka", "unit": "oz", "isGarnish": false}, {"quantity": "", "name": "Soda water", "unit": "", "isGarnish": false}, {"quantity": "3/4", "name": "Honey-hibiscus syrup*", "unit": "oz", "isGarnish": false}, {"quantity": "", "name": "Cucumber wheel", "unit": "", "isGarnish": true}], "preparation": "This drink is delicately pink and 100 percent spa day, which is exactly how I imagine the life and times of Joan Collins.\n\nIn a cocktail shaker, muddle the lime, cucumber and mint.\n\nAdd the syrup and vodka with plenty of ice, and shake until chilled.\n\nStrain over ice into a Collins glass, and top with soda water. Serve with a cucumber wheel for garnish.\n\n*Honey-hibiscus syrup: Bring 1/2 cup of honey and 1/2 cup of water to simmer, stirring to incorporate.\n\nRemove from heat, add 1 hibiscus tea bag, and let cool.\n\nRemove the tea bag and store in the refrigerator for up to a month.", "imageURL": "https://www.liquor.com/thmb/55jQ3xOz5HX5swUQRGkoWbv1YaQ=/960x0/filters:no_upscale():max_bytes(150000):strip_icc()/__opt__aboutcom__coeus__resources__content_migration__liquor__2016__08__18152127__vodka-joan-collins-720x720-recipe-d342e63ab4bd4ceaa91bba0b0b523f1d.jpg", "authorName": "Casey Elsass", "reviewCount": null, "avgRating": null}