{"name": "Kentucky Mule", "ingredients": [{"quantity": "2", "item": "Woodford Reserve bourbon", "unit": "oz"}, {"quantity": "1/2", "item": "Fresh lime juice", "unit": "oz"}, {"quantity": null, "item": "Ginger beer", "unit": "top"}], "garnish": ["Mint sprigs"], "glass": "Moscow Mule mug or highball", "preparation": "Add the bourbon and lime juice to a Moscow Mule mug or a highball glass.\nFill the mug or glass with ice and top with ginger beer.\nAdd mint sprigs for garnish.", "imageURL": "//cdn.liquor.com/wp-content/uploads/2018/03/21204112/kentucky-mule-720-720-recipe.jpg"}