{"name": "Macaulay Culkin", "ingredients": [{"quantity": "1", "item": "Blanco tequila", "unit": "oz"}, {"quantity": "1", "item": "Amaretto", "unit": "oz"}, {"quantity": "1/2", "item": "Fresh lemon juice", "unit": "oz"}, {"quantity": "1/2", "item": "Fresh lime juice", "unit": "oz"}, {"quantity": "1/2", "item": "Agave syrup", "unit": "oz"}, {"quantity": "1", "item": "Egg White", "unit": null}, {"quantity": "4", "item": "dashes", "unit": "dashes"}], "garnish": ["Rosemary sprig"], "glass": "Coupe", "preparation": "Add all ingredients into a shaker and dry-shake (no ice).\nAdd ice and shake again until well-chilled and a smooth froth forms.\nStrain into a coupe glass.\nGarnish with a rosemary sprig.", "imageURL": "//cdn.liquor.com/wp-content/uploads/2019/04/08131948/Macaulay-Culkin-720x720-recipe.jpg"}