{"name": "Mama, I'm Coming Home", "ingredients": [{"quantity": "1 1/2", "item": "Pecan-infused Cutty Sark blended scotch*", "unit": "oz"}, {"quantity": "3/4", "item": "cup Fonseca Bin No. 27 port", "unit": null}, {"quantity": "2", "item": "cup Apple cider", "unit": null}, {"quantity": "3/4", "item": "cup Honey syrup", "unit": null}, {"quantity": "2", "item": "Cinnamon sticks", "unit": null}, {"quantity": "7", "item": "Cloves", "unit": null}], "garnish": ["Soft caramel candy"], "glass": "Irish Coffee mug", "preparation": ".\nPlace all the ingredients in a pan, and bring to a boil.\nReduce the heat to low, and let simmer for 1 hour.\nDouble-strain the cinnamon sticks and cloves from the hot cider.\nPour into an Irish coffee mug.\nGarnish with a skewered soft caramel candy.\n*Pecan-infused Cutty Sark scotch: Place 1 16-oz package of raw pecans on a baking sheet, and sprinkle with salt and pepper. Place in an oven heated at 200 degrees F, and roast for 20 to 25 minutes, stirring halfway through. Let cool. Pour pecans and 1L scotch into a large airtight container, and let set and infuse for 1 week. Strain out solids.", "imageURL": "//cdn.liquor.com/wp-content/uploads/2017/12/06073301/Mama-Im-Coming-Home-720x720-recipe.jpg"}