{"name": "Matador Norte\u00f1o", "ingredients": [{"quantity": "2", "item": "Sotol", "unit": "oz"}, {"quantity": "3/4", "item": "Pineapple juice", "unit": "oz"}, {"quantity": "3/4", "item": "Fresh lemon juice", "unit": "oz"}, {"quantity": "1/2", "item": "Rich agave syrup (2 parts agave nectar, 1 part water)", "unit": "oz"}, {"quantity": "5", "item": "drops Habanero tincture*", "unit": null}], "garnish": [], "glass": "Cocktail", "preparation": "Add all ingredients to a shaker and fill with ice.\nShake, and strain into a cocktail glass.", "imageURL": "//cdn.liquor.com/wp-content/uploads/2015/10/02080646/Matador-Norteno-recipe.jpg"}