{"name": "Necromancer", "ingredients": [{"quantity": "3/4", "name": "Tenneyson Absinthe", "unit": "oz", "isGarnish": false}, {"quantity": "3/4", "name": "Lillet Blanc", "unit": "oz", "isGarnish": false}, {"quantity": "3/4", "name": "P\u00fcr Lik\u00f6r Blossom Elderflower Liqueur", "unit": "oz", "isGarnish": false}, {"quantity": "3/4", "name": "Lemon juice", "unit": "oz", "isGarnish": false}, {"quantity": "1", "name": "Gin", "unit": "dashes", "isGarnish": false}, {"quantity": "", "name": "1 Lemon twist", "unit": "", "isGarnish": true}], "preparation": "This absinthe tipple holds powerful magic.\n\nAdd all the ingredients to a shaker and fill with ice.\n\nShake, and strain into a coupe glass.\n\nGarnish with a lemon twist.", "imageURL": "https://www.liquor.com/thmb/FX8vPKQjLSFJbt6hwP5AseVbGwc=/960x0/filters:no_upscale():max_bytes(150000):strip_icc()/__opt__aboutcom__coeus__resources__content_migration__liquor__2014__03__recipe-Necromancer-f1e35d1b8ebb4f96b12cb5dc9390ff40.jpg", "authorName": "Mayur Subbarao", "reviewCount": null, "avgRating": null}