{"name": "New Orleans: #RAD", "ingredients": [{"quantity": "1", "name": "D\u2019USS\u00c9 Cognac", "unit": "oz", "isGarnish": false}, {"quantity": "3/4", "name": "Lemon juice", "unit": "oz", "isGarnish": false}, {"quantity": "1/2", "name": "St-Germain", "unit": "oz", "isGarnish": false}, {"quantity": "1/2", "name": "Strawberry pur\u00e9e", "unit": "oz", "isGarnish": false}, {"quantity": "3", "name": "Absinthe", "unit": "dashes", "isGarnish": false}, {"quantity": "", "name": "Sparkling ros\u00e9", "unit": "", "isGarnish": false}, {"quantity": "", "name": "Mini tiny rubber duckie", "unit": "", "isGarnish": true}], "preparation": "Pam Wiznitzer\u2019s bubbly New Orleans: #RAD was inspired by her favorite moment during the annual Tales of the Cocktail convention. Following the last Tales event on Sunday night, the industry takes over a local bar and breaks out the sparkling ros\u00e9 to the chant of \u201cros\u00e9 all day.\u201d Wiznitzer captured the energy of this moment with her specialty cocktail, made with cognac, St-Germain, strawberry puree and absinthe and topped with a float of sparkling ros\u00e9.\n\nShake all ingredients except for the sparkling ros\u00e9.\n\nPour into a white wine glass.\n\nTop with sparkling ros\u00e9.\n\nGarnish with mini tiny rubber duckie.", "imageURL": "https://www.liquor.com/thmb/00uiYSSXklS69CMx3rBDxuUatmk=/960x0/filters:no_upscale():max_bytes(150000):strip_icc()/__opt__aboutcom__coeus__resources__content_migration__liquor__2015__10__23105301__rad_500x500-39cf49c51d3e443cbbb73ef273c4fa4e.png", "authorName": "Pamela Wiznitzer", "reviewCount": null, "avgRating": null}