{"name": "Outlaws", "ingredients": [{"quantity": "1 1/2", "item": "Ardbeg 10-year-old scotch", "unit": "oz", "isGarnish": false}, {"quantity": "1/2", "item": "Fresh lime juice", "unit": "oz", "isGarnish": false}, {"quantity": "1/2", "item": "Cocchi Americano aperitivo", "unit": "oz", "isGarnish": false}, {"quantity": "1/2", "item": "Rothman & Winter orchard apricot liqueur", "unit": "oz", "isGarnish": false}, {"quantity": "3", "item": "Bittermens Xocolatl Mole bitters", "unit": "dashes", "isGarnish": false}, {"quantity": "", "item": "Star anise", "unit": "", "isGarnish": true}], "preparation": "This Washington, D.C.\u2013inspired cocktail has just the right amount of smoke and malt.\n\nAdd all the ingredients to a shaker with ice and shake.\n\nDouble-strain into a couple glass, and garnish with star anise.", "imageURL": "https://www.liquor.com/thmb/U8pd72xG1zDXlBhRQJaMPxpeGYw=/960x0/filters:no_upscale():max_bytes(150000):strip_icc()/__opt__aboutcom__coeus__resources__content_migration__liquor__2017__06__27150954__20170601_timmes_left_door_008-a9232ea542574e3aad077155ec9b7d76.jpg", "authorName": "Liquor.com", "reviewCount": null, "avgRating": null}