{"name": "Phoenix Colada", "ingredients": [{"quantity": "1 1/2", "item": "Coconut-infused Bluebird Distilling Sugarcane rum*", "unit": "oz", "isGarnish": false}, {"quantity": "1/2", "item": "Bluebird Distilling Four Grain bourbon", "unit": "oz", "isGarnish": false}, {"quantity": "1 1/2", "item": "Pineapple juice", "unit": "oz", "isGarnish": false}, {"quantity": "1/2", "item": "Demerara syrup", "unit": "oz", "isGarnish": false}, {"quantity": "2", "item": "Bittermens Elemakule Tiki bitters", "unit": "dashes", "isGarnish": false}, {"quantity": "", "item": "Gosling's Stormy ginger beer", "unit": "top", "isGarnish": false}, {"quantity": "", "item": "2 pineapple fronds", "unit": "", "isGarnish": true}, {"quantity": "", "item": "Grated nutmeg", "unit": "", "isGarnish": true}], "preparation": "Matt Giarratano, the beverage director at Phoenixville, Pa.\u2019s Bluebird Distilling, wanted to remove the endless sun-and-beach associations with his favorite tropical flavors\u2014rum, coconut and pineapple\u2014and added an element of what he calls everyday drinkability. Bourbon, rum and Tiki bitters balance the sweet, and the name is a nod to the Philadelphia suburb where the distillery and cocktail bar are located.\n\nThis recipe originally appeared as part of \u201cThe 5 Recipe Variations Every Dark \u2019N\u2019 Stormy Lover Should Know.\u201d\n\nAdd the rum, bourbon, juice, syrup and bitters into a shaker with ice, and shake until well-chilled.\n\nStrain into a Collins glass over fresh ice.\n\nTop with the ginger beer.\n\nGarnish with 2 pineapple fronds and freshly grated nutmeg.\n\n*Coconut-infused rum: Combine 1 750mL bottle of Bluebird Distilling Sugarcane rum and 4 cups flaked coconut in a nonreactive container like a large Mason jar. Let it set for 4 days, then strain out solids through a fine-mesh strainer.", "imageURL": "https://www.liquor.com/thmb/JrX6rxRWB_VHpc1L9AzN3GCsmvs=/960x0/filters:no_upscale():max_bytes(150000):strip_icc()/__opt__aboutcom__coeus__resources__content_migration__liquor__2018__01__17083044__Phoenix-Colada-720x720-recipe-b3528c7e832d43c3b3045b5233ad6ff9.jpg", "authorName": "Matt Giarratano", "reviewCount": null, "avgRating": null}