{"name": "Red Beans & Rice Orgeat", "ingredients": [{"quantity": "2", "item": "Dry red beans", "unit": "cup", "isGarnish": false}, {"quantity": "4", "item": "White rice", "unit": "cup", "isGarnish": false}, {"quantity": "2", "item": "Vodka", "unit": "oz", "isGarnish": false}, {"quantity": "2", "item": "Orange blossom water", "unit": "oz", "isGarnish": false}, {"quantity": "3", "item": "Vanilla beans", "unit": "", "isGarnish": false}, {"quantity": "8", "item": "Sugar", "unit": "cup", "isGarnish": false}], "preparation": "Orgeat, the staple sweetener used in Tiki drinks, is made with almonds. But if you have a nut allergy, this is a great alternative. The red beans give it the feel of adzuki (sweet red bean mash popular in Chinese pastries), and the citrus in orange blossom water complements the vanilla beans better and makes the orgeat a little more versatile for classic Tiki drinks.\n\nThis recipe originally appeared as part of \u201cThis Is the Only Nut-Free Orgeat Recipe You'll Ever Need.\u201d\n\nIn a large rondeau pot, toast beans and rice until lightly browned.\n\nAdd vodka, orange blossom water, vanilla beans and 8 cups water and bring to a boil.\n\nRemove from heat, strain liquid and reserve liquid.\n\nPut resulting mash back in pot, add 8 cups sugar and 8 cups water.\n\nBring to a boil, remove from heat, strain and reserve liquid.\n\nCombine mash and both reserved liquids.\n\nKeeps in refrigerator for up to one month.", "imageURL": "https://www.liquor.com/thmb/CDvM0n7No51M_amD4PanzoaTHbc=/960x0/filters:no_upscale():max_bytes(150000):strip_icc()/__opt__aboutcom__coeus__resources__content_migration__liquor__2019__11__14130852__Red-Beans-Rice-Orgeat-720x720-recipe-3fef43e426a644079b55913103d8eb3a.jpg", "authorName": "Tara Rizzi", "reviewCount": 6, "avgRating": 3.0}