{"name": "Royal Balmoral Punch", "ingredients": [{"quantity": "3", "item": "Glenfiddich 21-Year-Old Single Malt Scotch Whisky", "unit": "oz"}, {"quantity": "1", "item": "Tea Syrup", "unit": "oz"}, {"quantity": "2", "item": "Granny Smith apple juice", "unit": "oz"}, {"quantity": null, "item": "Lemonade", "unit": null}, {"quantity": null, "item": "Champagne", "unit": null}, {"quantity": null, "item": "Thistle", "unit": null}], "garnish": ["1\u00a0Lemon wheel"], "glass": "Teacup", "preparation": "Add the Scotch, syrup and apple juice to a teacup and add a large ice cube.\nTop with equal amounts of lemonade and Champagne.\nGarnish with a lemon wheel and thistle.\n(This recipe can multiplied to serve a crowd: Mix in a punch bowl with a large block of ice.).", "imageURL": "//cdn.liquor.com/wp-content/uploads/2011/01/royal-balmoral-punch1.jpg"}