{"name": "Spiced Chocolate", "ingredients": [{"quantity": "1", "name": "Patr\u00f3n XO Caf\u00e9 Liqueur", "unit": "oz", "isGarnish": false}, {"quantity": "1 1/2", "name": "Patr\u00f3n Reposado Tequila", "unit": "oz", "isGarnish": false}, {"quantity": "3/4", "name": "Dark chocolate liqueur", "unit": "oz", "isGarnish": false}, {"quantity": "", "name": "Fresh whipped cream", "unit": "", "isGarnish": false}, {"quantity": "", "name": "1 crushed red pepper", "unit": "", "isGarnish": true}], "preparation": "Red peppers. Chocolate liqueur. Tequila. Your tongue will dance.\n\nAdd all the ingredients except the whipped cream to a shaker and fill with ice.\n\nShake, and strain into a chilled old fashioned glass.\n\nLayer the top of the cocktail with a dollop of whipped cream and garnish with a large pinch of crushed red pepper.", "imageURL": "https://www.liquor.com/thmb/-xyqGY2ZScgFYYmATY_yfgiDWl0=/960x0/filters:no_upscale():max_bytes(150000):strip_icc()/__opt__aboutcom__coeus__resources__content_migration__liquor__2018__10__22115926__spiced-chocolate-720x720-recipe-9830e2c7fd36410b9d9387353be88a54.jpg", "authorName": "Liquor.com", "reviewCount": null, "avgRating": null}