{"name": "Spiced Pumpkin Flip", "ingredients": [{"quantity": "1", "item": "Bourbon", "unit": "oz", "isGarnish": false}, {"quantity": "1/2", "item": "Amaretto", "unit": "oz", "isGarnish": false}, {"quantity": "2", "item": "Pumpkin ale", "unit": "oz", "isGarnish": false}, {"quantity": "1/2", "item": "Agave nectar", "unit": "oz", "isGarnish": false}, {"quantity": "1", "item": "Pumpkin butter", "unit": "tsp", "isGarnish": false}, {"quantity": "1", "item": "Whole egg", "unit": "", "isGarnish": false}, {"quantity": "", "item": "Grated nutmeg", "unit": "", "isGarnish": true}], "preparation": "This seasonal riff on the classic Flip features pumpkin flavor in two forms.\n\nAdd all ingredients into a shaker and dry-shake until combined.\n\nAdd ice and shake very hard until chilled and frothy.\n\nStrain into a rocks glass.\n\nTop with grated nutmeg.", "imageURL": "https://www.liquor.com/thmb/Ht107Z0TieJI6v7b-cFmaC46Gag=/960x0/filters:no_upscale():max_bytes(150000):strip_icc()/__opt__aboutcom__coeus__resources__content_migration__liquor__2019__11__05101650__spiced-pumpkin-flip-720x720-recipe-f5bc543495b64c68a6913d717442bb01.jpg", "authorName": "Naren Young", "reviewCount": null, "avgRating": null}