{"name": "Stone Barn", "ingredients": [{"quantity": "1", "item": "Elijah Craig bourbon", "unit": "oz"}, {"quantity": "1/4", "item": "Cruzan black strap rum", "unit": "oz"}, {"quantity": "1/2", "item": "Domaine de Canton ginger liqueur", "unit": "oz"}, {"quantity": "3/4", "item": "Coconut syrup*", "unit": "oz"}, {"quantity": "3/4", "item": "Carrot juice**", "unit": "oz"}, {"quantity": "1/2", "item": "Fresh lemon juice", "unit": "oz"}, {"quantity": "4", "item": "Fresh dill pieces", "unit": null}], "garnish": ["Dill leaves; Straw"], "glass": "Pilsner", "preparation": "Add all the ingredients into a shaker with 3 Kold-draft ice cubes and shake (roughly 8 to 9 shakes).\nFine-strain into a pilsner glass over crushed ice.\nGarnish with dill leaves and 1 straw.\n*Coconut syrup: Toast 500g of coconut flakes until lightly browned under a grill, and remove from heat. Soak in 500 mL water, steep for 5 minutes, then blend ingredients with a hand mixer.\nAllow to sit for 5 more minutes, then fine-strain through cheesecloth. Weigh remaining liquid, then add double the weight in white caster sugar, dissolve using the hand blender, bottle and refrigerate.\n**Carrot juice: Juice 8 carrots and strain through a cheesecloth.", "imageURL": "//cdn.liquor.com/wp-content/uploads/2018/08/20095142/stone-barn-720x720-recipe.jpg"}