{"name": "Tequila Blood Orange Soda", "ingredients": [{"quantity": "1 1/2", "item": "Cazadores blanco tequila Buy Now", "unit": "oz"}, {"quantity": "1", "item": "Blood orange juice", "unit": "oz"}, {"quantity": "1/2", "item": "Fresh lime juice", "unit": "oz"}, {"quantity": "1/2", "item": "Agave nectar", "unit": "oz"}, {"quantity": null, "item": "Club soda", "unit": null}], "garnish": ["Mint sprig"], "glass": "Collins", "preparation": "Combine the tequila, blood orange and lime juices, and agave nectar in a shaker with ice, and shake.\nStrain into a Collins or Highball glass filled with ice, and top with the club soda.\nGarnish with a mint sprig.", "imageURL": "//cdn.liquor.com/wp-content/uploads/2017/08/25131639/BLOODORANGE-720x720.jpg"}