{"name": "The Apple Fell Far from the Tree", "ingredients": [{"quantity": "1 1/2", "item": "Butterfly-pea-flower-infused blanco tequila*", "unit": "oz"}, {"quantity": "1/2", "item": "Plantation Stiggins\u2019 Fancy Pineapple rum", "unit": "oz"}, {"quantity": "1/4", "item": "Hamilton pimento dram", "unit": "oz"}, {"quantity": "3/4", "item": "Fresh lime juice", "unit": "oz"}, {"quantity": "3/4", "item": "Fuji apple syrup**", "unit": "oz"}], "garnish": ["3 apple slices"], "glass": "Rocks", "preparation": "Add all the ingredients to a shaker with ice and shake.\nStrain into a rocks glass filled with fresh ice.\n*Butterfly-pea-flower-infused blanco tequila: Steep 1/2 cup \n in 1 750 mL bottle of tequila for 20 minutes.\n**Fuji apple syrup: Peel 12 Fuji apples with a citrus peeler, using 4 cuts to save the apple cores. In a saucepan, add peels and cores to 6 cups of sugar and 9 cups water. Bring to a boil and let simmer for 35 minutes. Strain out peels and cores, and keep refrigerated for up to 1 week.", "imageURL": "//cdn.liquor.com/wp-content/uploads/2017/10/25083056/The-Apple-Fell-Far-from-the-tree-720x720-recipe.jpg"}