{"name": "Ti\u2019 Bijou", "ingredients": [{"quantity": null, "item": "Absinthe", "unit": "rinse"}, {"quantity": "1", "item": "Boukman botanical rhum agricole (or Barbancourt blanc)", "unit": "oz"}, {"quantity": "1\u20442", "item": "London dry gin", "unit": "oz"}, {"quantity": "1\u20442", "item": "Dolin blanc vermouth", "unit": "oz"}, {"quantity": "1\u20442", "item": "Chamomile tea syrup*", "unit": "oz"}, {"quantity": "1", "item": "Salt", "unit": "pinch"}, {"quantity": "2", "item": "drops Orange bitters", "unit": null}]}