{"name": "Vesper", "ingredients": [{"quantity": "3", "item": "Gin", "unit": "oz"}, {"quantity": "1", "item": "Vodka", "unit": "oz"}, {"quantity": "1/2", "item": "Lillet blanc ap\u00e9ritif", "unit": "oz"}], "garnish": ["Lemon twist"], "glass": "Cocktail", "preparation": "Add all the ingredients into a mixing glass with ice and stir.\nStrain into a chilled cocktail glass.\nTwist a slice of lemon peel over the drink, rub along the rim of the glass, and drop it in.", "imageURL": "//cdn.liquor.com/wp-content/uploads/2018/01/29145254/vesper-720x720-recipe.jpg"}