{"name": "Vodka Tonic", "ingredients": [{"quantity": "2", "item": "vodka", "unit": "oz", "isGarnish": false}, {"quantity": "", "item": "tonic water", "unit": "top", "isGarnish": false}, {"quantity": "", "item": "squeeze of lemon", "unit": "", "isGarnish": false}, {"quantity": "", "item": "lemon peel", "unit": "", "isGarnish": true}], "preparation": "This classic vodka cocktail couldn\u2019t be easier to make.\n\nIn a Collins glass, add the vodka, fill with ice, top with the tonic water, and add a squeeze of lemon.\n\nGarnish with a lemon peel.", "imageURL": "https://www.liquor.com/thmb/7QwE6m52x-HvV_TtEQtzvfwe2Aw=/960x0/filters:no_upscale():max_bytes(150000):strip_icc()/__opt__aboutcom__coeus__resources__content_migration__liquor__2016__08__18132402__vodka-tonic-720x720-recipe-fafa4f1a65174441a71cf7462ada0db1.jpg", "authorName": "Cameron Dale", "reviewCount": 75, "avgRating": 4.5}